.coveragerc
.flake8
.pylintrc
MANIFEST.in
README.rst
setup.cfg
setup.py
tox.ini
atests/__init__.py
atests/conftest.py
atests/test_anypythonshell.py
atests/test_daemonizer.py
atests/test_remoterunner.py
atests/utils.py
docker-robottests-targets/docker-compose.yaml
docker-robottests-targets/docker-robottests
docker-robottests-targets/py27/Dockerfile
docker-robottests-targets/py38/Dockerfile
docker-robottests-targets/py38_no_python_symlink/Dockerfile
robottests/BackgroundRunner.py
robottests/ClusterExec.py
robottests/FileCopier.py
robottests/README.rst
robottests/SessionBroker.py
robottests/TestSession.py
robottests/examplehosts.py
robottests/filehelper.py
robottests/proxytest.py
robottests/targethosts.py
robottests/test_backgroundrunner.robot
robottests/test_broadcast_msgs.robot
robottests/test_create_directory.robot
robottests/test_filecopier.robot
robottests/test_remoterunner.robot
robottests/test_remoterunner_and_remotescript.robot
robottests/test_runnerterminal.robot
robottests/test_selfrepairingsession.robot
src/crl/__init__.py
src/crl.interactivesessions.egg-info/PKG-INFO
src/crl.interactivesessions.egg-info/SOURCES.txt
src/crl.interactivesessions.egg-info/dependency_links.txt
src/crl.interactivesessions.egg-info/entry_points.txt
src/crl.interactivesessions.egg-info/namespace_packages.txt
src/crl.interactivesessions.egg-info/requires.txt
src/crl.interactivesessions.egg-info/top_level.txt
src/crl/interactivesessions/InteractiveExecutor.py
src/crl/interactivesessions/InteractiveSession.py
src/crl/interactivesessions/InteractiveSessionExecutor.py
src/crl/interactivesessions/InteractiveSessions.py
src/crl/interactivesessions/RunnerHandler.py
src/crl/interactivesessions/RunnerSession.py
src/crl/interactivesessions/SelfRepairingSession.py
src/crl/interactivesessions/SessionManager.py
src/crl/interactivesessions/ShellSubprocess.py
src/crl/interactivesessions/__init__.py
src/crl/interactivesessions/_filecopier.py
src/crl/interactivesessions/_metasingleton.py
src/crl/interactivesessions/_pool.py
src/crl/interactivesessions/_process.py
src/crl/interactivesessions/_remoterunnerproxies.py
src/crl/interactivesessions/_runnerintarget.py
src/crl/interactivesessions/_runnerterminalloglevel.py
src/crl/interactivesessions/_targetproperties.py
src/crl/interactivesessions/_terminalpoolkey.py
src/crl/interactivesessions/_terminalpools.py
