Metadata-Version: 1.1
Name: crl.interactivesessions
Version: 1.3.0
Summary: Robot Framework test library collection on top of pexpect
Home-page: https://github.com/nokia/crl-interactivesessions
Author: Petri Huovinen
Author-email: petri.huovinen@nokia.com
License: BSD-3-Clause
Keywords: robotframework
Platform: UNKNOWN
Classifier: Intended Audience :: Developers
Classifier: License :: OSI Approved :: BSD License
Classifier: Programming Language :: Python :: 2
Classifier: Programming Language :: Python :: 2.7
Classifier: Programming Language :: Python :: 3
Classifier: Programming Language :: Python :: 3.6
Classifier: Programming Language :: Python :: 3.7
Classifier: Topic :: Software Development
